waveshare_touch_epaper/__init__.py
waveshare_touch_epaper/epaper_display.py
waveshare_touch_epaper/touch_screen.py
waveshare_touch_epaper-1.2.dist-info/LICENSE
waveshare_touch_epaper-1.2.dist-info/METADATA
waveshare_touch_epaper-1.2.dist-info/WHEEL
waveshare_touch_epaper-1.2.dist-info/top_level.txt
waveshare_touch_epaper-1.2.dist-info/RECORD
