Metadata-Version: 2.1
Name: waveshare_touch_epaper
Version: 1.2
Summary: module to control waveshare touch epaper displays
Author: Imam Usmani
Project-URL: Source Code, https://github.com/ImamAzim/waveshare-touch-epaper
Project-URL: Documentation, https://github.com/ImamAzim/waveshare-touch-epaper
Classifier: Intended Audience :: Developers
Classifier: Natural Language :: English
Classifier: Programming Language :: Python :: 3
Classifier: Operating System :: POSIX :: Linux
Requires-Python: >=3.7
License-File: LICENSE
Requires-Dist: gpiozero
Requires-Dist: rpi.gpio
Requires-Dist: smbus3
Requires-Dist: spidev
Requires-Dist: numpy
Requires-Dist: pillow
Requires-Dist: inputimeout
Provides-Extra: dev
Requires-Dist: pytest; extra == "dev"
Requires-Dist: flake8; extra == "dev"
Requires-Dist: ipython; extra == "dev"
Requires-Dist: build; extra == "dev"
Requires-Dist: twine; extra == "dev"
